__init__.py
dynalistTk.py
dynalistTk-1.2.dist-info/LICENSE
dynalistTk-1.2.dist-info/METADATA
dynalistTk-1.2.dist-info/WHEEL
dynalistTk-1.2.dist-info/top_level.txt
dynalistTk-1.2.dist-info/RECORD
